checkr/BaseRequest.py
checkr/ErrorBag.py
checkr/__init__.py
checkr/exceptions.py
checkr/rules_map.py
checkr/rules/Accepted.py
checkr/rules/Array.py
checkr/rules/ArrayOf.py
checkr/rules/BaseRule.py
checkr/rules/Between.py
checkr/rules/Boolean.py
checkr/rules/DateAfter.py
checkr/rules/DateAfterOrEqual.py
checkr/rules/DateBefore.py
checkr/rules/DateBeforeOrEqual.py
checkr/rules/Decimal.py
checkr/rules/Declined.py
checkr/rules/Email.py
checkr/rules/Endswith.py
checkr/rules/Gt.py
checkr/rules/Gte.py
checkr/rules/InArray.py
checkr/rules/Integer.py
checkr/rules/Ip.py
checkr/rules/Ipv4.py
checkr/rules/Ipv6.py
checkr/rules/Json.py
checkr/rules/Lowercase.py
checkr/rules/Lt.py
checkr/rules/Lte.py
checkr/rules/MacAddress.py
checkr/rules/Max.py
checkr/rules/MaxDigits.py
checkr/rules/Min.py
checkr/rules/MinDigits.py
checkr/rules/NotInArray.py
checkr/rules/Nullable.py
checkr/rules/Numeric.py
checkr/rules/Required.py
checkr/rules/Startswith.py
checkr/rules/String.py
checkr/rules/Ulid.py
checkr/rules/Uppercase.py
checkr/rules/Url.py
checkr/rules/Uuid.py
checkr/rules/__init__.py
checkr-0.1.3.dist-info/METADATA
checkr-0.1.3.dist-info/WHEEL
checkr-0.1.3.dist-info/licenses/LICENSE
checkr-0.1.3.dist-info/RECORD
