Metadata-Version: 2.1
Name: checkr
Version: 0.1.3
Summary: Data validation made easy
Project-URL: Homepage, https://github.com/celyes/checkr
Project-URL: Documentation, https://github.com/celyes/checkr#readme
Project-URL: Source, https://github.com/celyes/checkr
Author-email: Ilyes Chouia <ilyes.chouia@outlook.com>
License-Expression: MIT
License-File: LICENSE
Classifier: Development Status :: 3 - Alpha
Classifier: Environment :: Console
Classifier: Environment :: MacOS X
Classifier: Intended Audience :: Developers
Classifier: Intended Audience :: Information Technology
Classifier: Intended Audience :: System Administrators
Classifier: License :: OSI Approved :: MIT License
Classifier: Operating System :: POSIX :: Linux
Classifier: Operating System :: Unix
Classifier: Programming Language :: Python
Classifier: Programming Language :: Python :: 3.7
Classifier: Programming Language :: Python :: 3.8
Classifier: Programming Language :: Python :: 3.9
Classifier: Programming Language :: Python :: 3.10
Classifier: Programming Language :: Python :: 3.11
Classifier: Topic :: Internet
Classifier: Topic :: Software Development :: Libraries :: Python Modules
Requires-Python: >=3.7
Requires-Dist: pytest>=7.2.2
Requires-Dist: requests>=2.28.2
Requires-Dist: ulid-py>=1.1.0
Requires-Dist: validators>=0.20.0
